{".class": "MypyFile", "_fullname": "notary", "_name": null, "is_partial_stub_package": false, "is_stub": false, "names": {".class": "SymbolTable", "Any": {".class": "SymbolTableNode", "cross_ref": "typing.Any", "kind": "Gdef"}, "BadNotesFormat": {".class": "SymbolTableNode", "kind": "Gdef", "node": {".class": "TypeInfo", "_promote": null, "abstract_attributes": [], "bases": ["builtins.Exception"], "declared_metaclass": null, "defn": {".class": "ClassDef", "fullname": "notary.BadNotesFormat", "name": "BadNotesFormat", "type_vars": []}, "flags": [], "fullname": "notary.BadNotesFormat", "metaclass_type": null, "metadata": {}, "module_name": "notary", "mro": ["notary.BadNotesFormat", "builtins.Exception", "builtins.BaseException", "builtins.object"], "names": {".class": "SymbolTable"}, "tuple_type": null, "type_vars": [], "typeddict_type": null}}, "Iterable": {".class": "SymbolTableNode", "cross_ref": "typing.Iterable", "kind": "Gdef"}, "Iterator": {".class": "SymbolTableNode", "cross_ref": "typing.Iterator", "kind": "Gdef"}, "List": {".class": "SymbolTableNode", "cross_ref": "typing.List", "kind": "Gdef"}, "MAX_COLUMNS_DEFAULT": {".class": "SymbolTableNode", "kind": "Gdef", "node": {".class": "Var", "flags": [], "fullname": "notary.MAX_COLUMNS_DEFAULT", "name": "MAX_COLUMNS_DEFAULT", "type": "builtins.int"}}, "NamedTuple": {".class": "SymbolTableNode", "cross_ref": "typing.NamedTuple", "kind": "Gdef"}, "NotASection": {".class": "SymbolTableNode", "kind": "Gdef", "node": {".class": "TypeInfo", "_promote": null, "abstract_attributes": [], "bases": ["builtins.Exception"], "declared_metaclass": null, "defn": {".class": "ClassDef", "fullname": "notary.NotASection", "name": "NotASection", "type_vars": []}, "flags": [], "fullname": "notary.NotASection", "metaclass_type": null, "metadata": {}, "module_name": "notary", "mro": ["notary.NotASection", "builtins.Exception", "builtins.BaseException", "builtins.object"], "names": {".class": "SymbolTable"}, "tuple_type": null, "type_vars": [], "typeddict_type": null}}, "Optional": {".class": "SymbolTableNode", "cross_ref": "typing.Optional", "kind": "Gdef"}, "Section": {".class": "SymbolTableNode", "kind": "Gdef", "node": {".class": "TypeInfo", "_promote": null, "abstract_attributes": [], "bases": [{".class": "Instance", "args": ["builtins.object"], "type_ref": "builtins.tuple"}], "declared_metaclass": null, "defn": {".class": "ClassDef", "fullname": "notary.Section", "name": "Section", "type_vars": []}, "flags": ["is_named_tuple"], "fullname": "notary.Section", "metaclass_type": null, "metadata": {}, "module_name": "notary", "mro": ["notary.Section", "builtins.tuple", "typing.Sequence", "typing.Collection", "typing.Sized", "typing.Iterable", "typing.Container", "typing.Reversible", "builtins.object"], "names": {".class": "SymbolTable", "__annotations__": {".class": "SymbolTableNode", "kind": "Mdef", "node": {".class": "Var", "flags": ["is_initialized_in_class"], "fullname": "notary.Section.__annotations__", "name": "__annotations__", "type": {".class": "Instance", "args": ["builtins.str", {".class": "AnyType", "missing_import_name": null, "source_any": null, "type_of_any": "special_form"}], "type_ref": "builtins.dict"}}}, "__doc__": {".class": "SymbolTableNode", "kind": "Mdef", "node": {".class": "Var", "flags": ["is_initialized_in_class"], "fullname": "notary.Section.__doc__", "name": "__doc__", "type": "builtins.str"}}, "__init__": {".class": "SymbolTableNode", "kind": "Mdef", "node": {".class": "FuncDef", "arg_kinds": [0, 0, 0], "arg_names": ["self", "text", "kind"], "flags": [], "fullname": "notary.Section.__init__", "name": "__init__", "type": {".class": "CallableType", "arg_kinds": [0, 0, 0], "arg_names": ["self", "text", "kind"], "arg_types": [{".class": "TypeVarType", "fullname": "NT", "id": 1, "name": "NT", "upper_bound": {".class": "TupleType", "fallback": {".class": "Instance", "args": ["builtins.object"], "type_ref": "builtins.tuple"}, "implicit": false, "items": ["builtins.str", "builtins.int"]}, "values": [], "variance": 0}, "builtins.str", "builtins.int"], "bound_args": [], "def_extras": {}, "fallback": "builtins.function", "implicit": false, "is_classmethod_class": false, "is_ellipsis_args": false, "name": "__init__ of Section", "ret_type": {".class": "NoneTyp"}, "variables": [{".class": "TypeVarDef", "fullname": "NT", "id": 1, "name": "NT", "upper_bound": {".class": "TupleType", "fallback": {".class": "Instance", "args": ["builtins.object"], "type_ref": "builtins.tuple"}, "implicit": false, "items": ["builtins.str", "builtins.int"]}, "values": [], "variance": 0}]}}}, "_asdict": {".class": "SymbolTableNode", "kind": "Mdef", "node": {".class": "FuncDef", "arg_kinds": [0], "arg_names": ["self"], "flags": [], "fullname": "notary.Section._asdict", "name": "_asdict", "type": {".class": "CallableType", "arg_kinds": [0], "arg_names": ["self"], "arg_types": [{".class": "TypeVarType", "fullname": "NT", "id": 1, "name": "NT", "upper_bound": {".class": "TupleType", "fallback": {".class": "Instance", "args": ["builtins.object"], "type_ref": "builtins.tuple"}, "implicit": false, "items": ["builtins.str", "builtins.int"]}, "values": [], "variance": 0}], "bound_args": [], "def_extras": {}, "fallback": "builtins.function", "implicit": false, "is_classmethod_class": false, "is_ellipsis_args": false, "name": "_asdict of Section", "ret_type": {".class": "Instance", "args": ["builtins.str", {".class": "AnyType", "missing_import_name": null, "source_any": null, "type_of_any": "special_form"}], "type_ref": "builtins.dict"}, "variables": [{".class": "TypeVarDef", "fullname": "NT", "id": 1, "name": "NT", "upper_bound": {".class": "TupleType", "fallback": {".class": "Instance", "args": ["builtins.object"], "type_ref": "builtins.tuple"}, "implicit": false, "items": ["builtins.str", "builtins.int"]}, "values": [], "variance": 0}]}}}, "_field_defaults": {".class": "SymbolTableNode", "kind": "Mdef", "node": {".class": "Var", "flags": ["is_initialized_in_class"], "fullname": "notary.Section._field_defaults", "name": "_field_defaults", "type": {".class": "Instance", "args": ["builtins.str", {".class": "AnyType", "missing_import_name": null, "source_any": null, "type_of_any": "special_form"}], "type_ref": "builtins.dict"}}}, "_field_types": {".class": "SymbolTableNode", "kind": "Mdef", "node": {".class": "Var", "flags": ["is_initialized_in_class"], "fullname": "notary.Section._field_types", "name": "_field_types", "type": {".class": "Instance", "args": ["builtins.str", {".class": "AnyType", "missing_import_name": null, "source_any": null, "type_of_any": "special_form"}], "type_ref": "builtins.dict"}}}, "_fields": {".class": "SymbolTableNode", "kind": "Mdef", "node": {".class": "Var", "flags": ["is_initialized_in_class"], "fullname": "notary.Section._fields", "name": "_fields", "type": {".class": "TupleType", "fallback": {".class": "Instance", "args": [{".class": "AnyType", "missing_import_name": null, "source_any": null, "type_of_any": "special_form"}], "type_ref": "builtins.tuple"}, "implicit": false, "items": ["builtins.str", "builtins.str"]}}}, "_make": {".class": "SymbolTableNode", "kind": "Mdef", "node": {".class": "Decorator", "func": {".class": "FuncDef", "arg_kinds": [0, 0, 5, 5], "arg_names": ["cls", "iterable", "new", "len"], "flags": ["is_class"], "fullname": "notary.Section._make", "name": "_make", "type": {".class": "CallableType", "arg_kinds": [0, 0, 5, 5], "arg_names": ["cls", "iterable", "new", "len"], "arg_types": [{".class": "TypeType", "item": {".class": "TypeVarType", "fullname": "NT", "id": 1, "name": "NT", "upper_bound": {".class": "TupleType", "fallback": {".class": "Instance", "args": ["builtins.object"], "type_ref": "builtins.tuple"}, "implicit": false, "items": ["builtins.str", "builtins.int"]}, "values": [], "variance": 0}}, {".class": "Instance", "args": [{".class": "AnyType", "missing_import_name": null, "source_any": null, "type_of_any": "special_form"}], "type_ref": "typing.Iterable"}, {".class": "AnyType", "missing_import_name": null, "source_any": null, "type_of_any": "special_form"}, {".class": "AnyType", "missing_import_name": null, "source_any": null, "type_of_any": "special_form"}], "bound_args": [], "def_extras": {}, "fallback": "builtins.function", "implicit": false, "is_classmethod_class": false, "is_ellipsis_args": false, "name": "_make of Section", "ret_type": {".class": "TypeVarType", "fullname": "NT", "id": 1, "name": "NT", "upper_bound": {".class": "TupleType", "fallback": {".class": "Instance", "args": ["builtins.object"], "type_ref": "builtins.tuple"}, "implicit": false, "items": ["builtins.str", "builtins.int"]}, "values": [], "variance": 0}, "variables": [{".class": "TypeVarDef", "fullname": "NT", "id": 1, "name": "NT", "upper_bound": {".class": "TupleType", "fallback": {".class": "Instance", "args": ["builtins.object"], "type_ref": "builtins.tuple"}, "implicit": false, "items": ["builtins.str", "builtins.int"]}, "values": [], "variance": 0}]}}, "is_overload": false, "var": {".class": "Var", "flags": ["is_classmethod"], "fullname": "notary.Section._make", "name": "_make", "type": {".class": "CallableType", "arg_kinds": [0, 0, 5, 5], "arg_names": ["cls", "iterable", "new", "len"], "arg_types": [{".class": "TypeType", "item": {".class": "TypeVarType", "fullname": "NT", "id": 1, "name": "NT", "upper_bound": {".class": "TupleType", "fallback": {".class": "Instance", "args": ["builtins.object"], "type_ref": "builtins.tuple"}, "implicit": false, "items": ["builtins.str", "builtins.int"]}, "values": [], "variance": 0}}, {".class": "Instance", "args": [{".class": "AnyType", "missing_import_name": null, "source_any": null, "type_of_any": "special_form"}], "type_ref": "typing.Iterable"}, {".class": "AnyType", "missing_import_name": null, "source_any": null, "type_of_any": "special_form"}, {".class": "AnyType", "missing_import_name": null, "source_any": null, "type_of_any": "special_form"}], "bound_args": [], "def_extras": {}, "fallback": "builtins.function", "implicit": false, "is_classmethod_class": false, "is_ellipsis_args": false, "name": "_make of Section", "ret_type": {".class": "TypeVarType", "fullname": "NT", "id": 1, "name": "NT", "upper_bound": {".class": "TupleType", "fallback": {".class": "Instance", "args": ["builtins.object"], "type_ref": "builtins.tuple"}, "implicit": false, "items": ["builtins.str", "builtins.int"]}, "values": [], "variance": 0}, "variables": [{".class": "TypeVarDef", "fullname": "NT", "id": 1, "name": "NT", "upper_bound": {".class": "TupleType", "fallback": {".class": "Instance", "args": ["builtins.object"], "type_ref": "builtins.tuple"}, "implicit": false, "items": ["builtins.str", "builtins.int"]}, "values": [], "variance": 0}]}}}}, "_replace": {".class": "SymbolTableNode", "kind": "Mdef", "node": {".class": "FuncDef", "arg_kinds": [0, 5, 5], "arg_names": ["self", "text", "kind"], "flags": [], "fullname": "notary.Section._replace", "name": "_replace", "type": {".class": "CallableType", "arg_kinds": [0, 5, 5], "arg_names": ["self", "text", "kind"], "arg_types": [{".class": "TypeVarType", "fullname": "NT", "id": 1, "name": "NT", "upper_bound": {".class": "TupleType", "fallback": {".class": "Instance", "args": ["builtins.object"], "type_ref": "builtins.tuple"}, "implicit": false, "items": ["builtins.str", "builtins.int"]}, "values": [], "variance": 0}, "builtins.str", "builtins.int"], "bound_args": [], "def_extras": {}, "fallback": "builtins.function", "implicit": false, "is_classmethod_class": false, "is_ellipsis_args": false, "name": "_replace of Section", "ret_type": {".class": "TypeVarType", "fullname": "NT", "id": 1, "name": "NT", "upper_bound": {".class": "TupleType", "fallback": {".class": "Instance", "args": ["builtins.object"], "type_ref": "builtins.tuple"}, "implicit": false, "items": ["builtins.str", "builtins.int"]}, "values": [], "variance": 0}, "variables": [{".class": "TypeVarDef", "fullname": "NT", "id": 1, "name": "NT", "upper_bound": {".class": "TupleType", "fallback": {".class": "Instance", "args": ["builtins.object"], "type_ref": "builtins.tuple"}, "implicit": false, "items": ["builtins.str", "builtins.int"]}, "values": [], "variance": 0}]}}}, "_source": {".class": "SymbolTableNode", "kind": "Mdef", "node": {".class": "Var", "flags": ["is_initialized_in_class"], "fullname": "notary.Section._source", "name": "_source", "type": "builtins.str"}}, "body": {".class": "SymbolTableNode", "kind": "Mdef", "node": {".class": "Decorator", "func": {".class": "FuncDef", "arg_kinds": [], "arg_names": [], "flags": ["is_static", "is_decorated"], "fullname": "notary.Section.body", "name": "body", "type": {".class": "CallableType", "arg_kinds": [], "arg_names": [], "arg_types": [], "bound_args": [], "def_extras": {"first_arg": null}, "fallback": "builtins.function", "implicit": false, "is_classmethod_class": false, "is_ellipsis_args": false, "name": "body of Section", "ret_type": "builtins.int", "variables": []}}, "is_overload": false, "var": {".class": "Var", "flags": ["is_initialized_in_class", "is_staticmethod"], "fullname": null, "name": "body", "type": {".class": "CallableType", "arg_kinds": [], "arg_names": [], "arg_types": [], "bound_args": [], "def_extras": {"first_arg": null}, "fallback": "builtins.function", "implicit": false, "is_classmethod_class": false, "is_ellipsis_args": false, "name": "body of Section", "ret_type": "builtins.int", "variables": []}}}}, "formatted": {".class": "SymbolTableNode", "kind": "Mdef", "node": {".class": "FuncDef", "arg_kinds": [0, 0], "arg_names": ["self", "max_columns"], "flags": [], "fullname": "notary.Section.formatted", "name": "formatted", "type": {".class": "CallableType", "arg_kinds": [0, 0], "arg_names": ["self", "max_columns"], "arg_types": [{".class": "TupleType", "fallback": "notary.Section", "implicit": false, "items": ["builtins.str", "builtins.int"]}, "builtins.int"], "bound_args": [], "def_extras": {"first_arg": "self"}, "fallback": "builtins.function", "implicit": false, "is_classmethod_class": false, "is_ellipsis_args": false, "name": "formatted of Section", "ret_type": "builtins.str", "variables": []}}}, "is_body_line": {".class": "SymbolTableNode", "kind": "Mdef", "node": {".class": "Decorator", "func": {".class": "FuncDef", "arg_kinds": [0], "arg_names": ["line"], "flags": ["is_static", "is_decorated"], "fullname": "notary.Section.is_body_line", "name": "is_body_line", "type": {".class": "CallableType", "arg_kinds": [0], "arg_names": ["line"], "arg_types": ["builtins.str"], "bound_args": [], "def_extras": {"first_arg": null}, "fallback": "builtins.function", "implicit": false, "is_classmethod_class": false, "is_ellipsis_args": false, "name": "is_body_line of Section", "ret_type": "builtins.bool", "variables": []}}, "is_overload": false, "var": {".class": "Var", "flags": ["is_initialized_in_class", "is_staticmethod"], "fullname": null, "name": "is_body_line", "type": {".class": "CallableType", "arg_kinds": [0], "arg_names": ["line"], "arg_types": ["builtins.str"], "bound_args": [], "def_extras": {"first_arg": null}, "fallback": "builtins.function", "implicit": false, "is_classmethod_class": false, "is_ellipsis_args": false, "name": "is_body_line of Section", "ret_type": "builtins.bool", "variables": []}}}}, "is_subtitle": {".class": "SymbolTableNode", "kind": "Mdef", "node": {".class": "Decorator", "func": {".class": "FuncDef", "arg_kinds": [0], "arg_names": ["line"], "flags": ["is_static", "is_decorated"], "fullname": "notary.Section.is_subtitle", "name": "is_subtitle", "type": {".class": "CallableType", "arg_kinds": [0], "arg_names": ["line"], "arg_types": ["builtins.str"], "bound_args": [], "def_extras": {"first_arg": null}, "fallback": "builtins.function", "implicit": false, "is_classmethod_class": false, "is_ellipsis_args": false, "name": "is_subtitle of Section", "ret_type": "builtins.bool", "variables": []}}, "is_overload": false, "var": {".class": "Var", "flags": ["is_initialized_in_class", "is_staticmethod"], "fullname": null, "name": "is_subtitle", "type": {".class": "CallableType", "arg_kinds": [0], "arg_names": ["line"], "arg_types": ["builtins.str"], "bound_args": [], "def_extras": {"first_arg": null}, "fallback": "builtins.function", "implicit": false, "is_classmethod_class": false, "is_ellipsis_args": false, "name": "is_subtitle of Section", "ret_type": "builtins.bool", "variables": []}}}}, "is_table_of_contents_line": {".class": "SymbolTableNode", "kind": "Mdef", "node": {".class": "Decorator", "func": {".class": "FuncDef", "arg_kinds": [0], "arg_names": ["line"], "flags": ["is_static", "is_decorated"], "fullname": "notary.Section.is_table_of_contents_line", "name": "is_table_of_contents_line", "type": {".class": "CallableType", "arg_kinds": [0], "arg_names": ["line"], "arg_types": ["builtins.str"], "bound_args": [], "def_extras": {"first_arg": null}, "fallback": "builtins.function", "implicit": false, "is_classmethod_class": false, "is_ellipsis_args": false, "name": "is_table_of_contents_line of Section", "ret_type": "builtins.bool", "variables": []}}, "is_overload": false, "var": {".class": "Var", "flags": ["is_initialized_in_class", "is_staticmethod"], "fullname": null, "name": "is_table_of_contents_line", "type": {".class": "CallableType", "arg_kinds": [0], "arg_names": ["line"], "arg_types": ["builtins.str"], "bound_args": [], "def_extras": {"first_arg": null}, "fallback": "builtins.function", "implicit": false, "is_classmethod_class": false, "is_ellipsis_args": false, "name": "is_table_of_contents_line of Section", "ret_type": "builtins.bool", "variables": []}}}}, "is_title": {".class": "SymbolTableNode", "kind": "Mdef", "node": {".class": "Decorator", "func": {".class": "FuncDef", "arg_kinds": [0], "arg_names": ["line"], "flags": ["is_static", "is_decorated"], "fullname": "notary.Section.is_title", "name": "is_title", "type": {".class": "CallableType", "arg_kinds": [0], "arg_names": ["line"], "arg_types": ["builtins.str"], "bound_args": [], "def_extras": {"first_arg": null}, "fallback": "builtins.function", "implicit": false, "is_classmethod_class": false, "is_ellipsis_args": false, "name": "is_title of Section", "ret_type": "builtins.bool", "variables": []}}, "is_overload": false, "var": {".class": "Var", "flags": ["is_initialized_in_class", "is_staticmethod"], "fullname": null, "name": "is_title", "type": {".class": "CallableType", "arg_kinds": [0], "arg_names": ["line"], "arg_types": ["builtins.str"], "bound_args": [], "def_extras": {"first_arg": null}, "fallback": "builtins.function", "implicit": false, "is_classmethod_class": false, "is_ellipsis_args": false, "name": "is_title of Section", "ret_type": "builtins.bool", "variables": []}}}}, "kind": {".class": "SymbolTableNode", "kind": "Mdef", "node": {".class": "Var", "flags": ["is_property"], "fullname": "notary.Section.kind", "name": "kind", "type": "builtins.int"}}, "subtitle": {".class": "SymbolTableNode", "kind": "Mdef", "node": {".class": "Decorator", "func": {".class": "FuncDef", "arg_kinds": [], "arg_names": [], "flags": ["is_static", "is_decorated"], "fullname": "notary.Section.subtitle", "name": "subtitle", "type": {".class": "CallableType", "arg_kinds": [], "arg_names": [], "arg_types": [], "bound_args": [], "def_extras": {"first_arg": null}, "fallback": "builtins.function", "implicit": false, "is_classmethod_class": false, "is_ellipsis_args": false, "name": "subtitle of Section", "ret_type": "builtins.int", "variables": []}}, "is_overload": false, "var": {".class": "Var", "flags": ["is_initialized_in_class", "is_staticmethod"], "fullname": null, "name": "subtitle", "type": {".class": "CallableType", "arg_kinds": [], "arg_names": [], "arg_types": [], "bound_args": [], "def_extras": {"first_arg": null}, "fallback": "builtins.function", "implicit": false, "is_classmethod_class": false, "is_ellipsis_args": false, "name": "subtitle of Section", "ret_type": "builtins.int", "variables": []}}}}, "table_of_contents": {".class": "SymbolTableNode", "kind": "Mdef", "node": {".class": "Decorator", "func": {".class": "FuncDef", "arg_kinds": [], "arg_names": [], "flags": ["is_static", "is_decorated"], "fullname": "notary.Section.table_of_contents", "name": "table_of_contents", "type": {".class": "CallableType", "arg_kinds": [], "arg_names": [], "arg_types": [], "bound_args": [], "def_extras": {"first_arg": null}, "fallback": "builtins.function", "implicit": false, "is_classmethod_class": false, "is_ellipsis_args": false, "name": "table_of_contents of Section", "ret_type": "builtins.int", "variables": []}}, "is_overload": false, "var": {".class": "Var", "flags": ["is_initialized_in_class", "is_staticmethod"], "fullname": null, "name": "table_of_contents", "type": {".class": "CallableType", "arg_kinds": [], "arg_names": [], "arg_types": [], "bound_args": [], "def_extras": {"first_arg": null}, "fallback": "builtins.function", "implicit": false, "is_classmethod_class": false, "is_ellipsis_args": false, "name": "table_of_contents of Section", "ret_type": "builtins.int", "variables": []}}}}, "text": {".class": "SymbolTableNode", "kind": "Mdef", "node": {".class": "Var", "flags": ["is_property"], "fullname": "notary.Section.text", "name": "text", "type": "builtins.str"}}, "title": {".class": "SymbolTableNode", "kind": "Mdef", "node": {".class": "Decorator", "func": {".class": "FuncDef", "arg_kinds": [], "arg_names": [], "flags": ["is_static", "is_decorated"], "fullname": "notary.Section.title", "name": "title", "type": {".class": "CallableType", "arg_kinds": [], "arg_names": [], "arg_types": [], "bound_args": [], "def_extras": {"first_arg": null}, "fallback": "builtins.function", "implicit": false, "is_classmethod_class": false, "is_ellipsis_args": false, "name": "title of Section", "ret_type": "builtins.int", "variables": []}}, "is_overload": false, "var": {".class": "Var", "flags": ["is_initialized_in_class", "is_staticmethod"], "fullname": null, "name": "title", "type": {".class": "CallableType", "arg_kinds": [], "arg_names": [], "arg_types": [], "bound_args": [], "def_extras": {"first_arg": null}, "fallback": "builtins.function", "implicit": false, "is_classmethod_class": false, "is_ellipsis_args": false, "name": "title of Section", "ret_type": "builtins.int", "variables": []}}}}}, "tuple_type": {".class": "TupleType", "fallback": {".class": "Instance", "args": ["builtins.object"], "type_ref": "builtins.tuple"}, "implicit": false, "items": ["builtins.str", "builtins.int"]}, "type_vars": [], "typeddict_type": null}}, "Tuple": {".class": "SymbolTableNode", "cross_ref": "typing.Tuple", "kind": "Gdef"}, "__doc__": {".class": "SymbolTableNode", "kind": "Gdef", "node": {".class": "Var", "flags": [], "fullname": "notary.__doc__", "name": "__doc__", "type": "builtins.str"}}, "__file__": {".class": "SymbolTableNode", "kind": "Gdef", "node": {".class": "Var", "flags": [], "fullname": "notary.__file__", "name": "__file__", "type": "builtins.str"}}, "__name__": {".class": "SymbolTableNode", "kind": "Gdef", "node": {".class": "Var", "flags": [], "fullname": "notary.__name__", "name": "__name__", "type": "builtins.str"}}, "__package__": {".class": "SymbolTableNode", "kind": "Gdef", "node": {".class": "Var", "flags": [], "fullname": "notary.__package__", "name": "__package__", "type": "builtins.str"}}, "annotations": {".class": "SymbolTableNode", "cross_ref": "__future__.annotations", "kind": "Gdef"}, "argparse": {".class": "SymbolTableNode", "cross_ref": "argparse", "kind": "ModuleRef"}, "enum": {".class": "SymbolTableNode", "cross_ref": "enum", "kind": "ModuleRef"}, "first_word": {".class": "SymbolTableNode", "kind": "Gdef", "node": {".class": "FuncDef", "arg_kinds": [0], "arg_names": ["s"], "flags": [], "fullname": "notary.first_word", "name": "first_word", "type": {".class": "CallableType", "arg_kinds": [0], "arg_names": ["s"], "arg_types": ["builtins.str"], "bound_args": [], "def_extras": {"first_arg": null}, "fallback": "builtins.function", "implicit": false, "is_classmethod_class": false, "is_ellipsis_args": false, "name": "first_word", "ret_type": "builtins.str", "variables": []}}}, "format_notes": {".class": "SymbolTableNode", "kind": "Gdef", "node": {".class": "FuncDef", "arg_kinds": [0, 0], "arg_names": ["notes", "max_columns"], "flags": [], "fullname": "notary.format_notes", "name": "format_notes", "type": {".class": "CallableType", "arg_kinds": [0, 0], "arg_names": ["notes", "max_columns"], "arg_types": ["builtins.str", "builtins.int"], "bound_args": [], "def_extras": {"first_arg": null}, "fallback": "builtins.function", "implicit": false, "is_classmethod_class": false, "is_ellipsis_args": false, "name": "format_notes", "ret_type": "builtins.str", "variables": []}}}, "format_sections": {".class": "SymbolTableNode", "kind": "Gdef", "node": {".class": "FuncDef", "arg_kinds": [0, 0], "arg_names": ["sections", "max_columns"], "flags": [], "fullname": "notary.format_sections", "name": "format_sections", "type": {".class": "CallableType", "arg_kinds": [0, 0], "arg_names": ["sections", "max_columns"], "arg_types": [{".class": "Instance", "args": [{".class": "TupleType", "fallback": "notary.Section", "implicit": false, "items": ["builtins.str", "builtins.int"]}], "type_ref": "typing.Iterable"}, "builtins.int"], "bound_args": [], "def_extras": {"first_arg": null}, "fallback": "builtins.function", "implicit": false, "is_classmethod_class": false, "is_ellipsis_args": false, "name": "format_sections", "ret_type": "builtins.str", "variables": []}}}, "functools": {".class": "SymbolTableNode", "cross_ref": "functools", "kind": "ModuleRef"}, "io": {".class": "SymbolTableNode", "cross_ref": "io", "kind": "ModuleRef"}, "itertools": {".class": "SymbolTableNode", "cross_ref": "itertools", "kind": "ModuleRef"}, "main": {".class": "SymbolTableNode", "kind": "Gdef", "node": {".class": "FuncDef", "arg_kinds": [], "arg_names": [], "flags": [], "fullname": "notary.main", "name": "main", "type": {".class": "CallableType", "arg_kinds": [], "arg_names": [], "arg_types": [], "bound_args": [], "def_extras": {"first_arg": null}, "fallback": "builtins.function", "implicit": false, "is_classmethod_class": false, "is_ellipsis_args": false, "name": "main", "ret_type": {".class": "NoneTyp"}, "variables": []}}}, "operator": {".class": "SymbolTableNode", "cross_ref": "operator", "kind": "ModuleRef"}, "parse_args": {".class": "SymbolTableNode", "kind": "Gdef", "node": {".class": "FuncDef", "arg_kinds": [], "arg_names": [], "flags": [], "fullname": "notary.parse_args", "name": "parse_args", "type": {".class": "CallableType", "arg_kinds": [], "arg_names": [], "arg_types": [], "bound_args": [], "def_extras": {"first_arg": null}, "fallback": "builtins.function", "implicit": false, "is_classmethod_class": false, "is_ellipsis_args": false, "name": "parse_args", "ret_type": {".class": "AnyType", "missing_import_name": null, "source_any": null, "type_of_any": "explicit"}, "variables": []}}}, "parse_notes": {".class": "SymbolTableNode", "kind": "Gdef", "node": {".class": "FuncDef", "arg_kinds": [0], "arg_names": ["notes"], "flags": ["is_generator"], "fullname": "notary.parse_notes", "name": "parse_notes", "type": {".class": "CallableType", "arg_kinds": [0], "arg_names": ["notes"], "arg_types": ["builtins.str"], "bound_args": [], "def_extras": {"first_arg": null}, "fallback": "builtins.function", "implicit": false, "is_classmethod_class": false, "is_ellipsis_args": false, "name": "parse_notes", "ret_type": {".class": "Instance", "args": [{".class": "TupleType", "fallback": "notary.Section", "implicit": false, "items": ["builtins.str", "builtins.int"]}], "type_ref": "typing.Iterable"}, "variables": []}}}, "re": {".class": "SymbolTableNode", "cross_ref": "re", "kind": "ModuleRef"}, "read_file": {".class": "SymbolTableNode", "kind": "Gdef", "node": {".class": "FuncDef", "arg_kinds": [0], "arg_names": ["file_name"], "flags": [], "fullname": "notary.read_file", "name": "read_file", "type": {".class": "CallableType", "arg_kinds": [0], "arg_names": ["file_name"], "arg_types": ["builtins.str"], "bound_args": [], "def_extras": {"first_arg": null}, "fallback": "builtins.function", "implicit": false, "is_classmethod_class": false, "is_ellipsis_args": false, "name": "read_file", "ret_type": "builtins.str", "variables": []}}}, "write_to_file": {".class": "SymbolTableNode", "kind": "Gdef", "node": {".class": "FuncDef", "arg_kinds": [0, 0], "arg_names": ["file_name", "content"], "flags": [], "fullname": "notary.write_to_file", "name": "write_to_file", "type": {".class": "CallableType", "arg_kinds": [0, 0], "arg_names": ["file_name", "content"], "arg_types": ["builtins.str", "builtins.str"], "bound_args": [], "def_extras": {"first_arg": null}, "fallback": "builtins.function", "implicit": false, "is_classmethod_class": false, "is_ellipsis_args": false, "name": "write_to_file", "ret_type": {".class": "NoneTyp"}, "variables": []}}}}, "path": "notary.py"}
